{
  "schema_version": 1,
  "name": "oscar_lic_research_repo",
  "version": "0.2.0-research-pass",
  "snapshot_date": "2026-06-25",
  "purpose": "Self-bootstrapping and active OSCAR-LIC LIC/OCR-aware compression research repository",
  "paper_registry_records": 58,
  "experiment_matrix_records": 37,
  "unit_tests_last_passed": 34,
  "toy_manifest_records": 5,
  "cuda_validated": true,
  "workspace_state": "eval300_frozen_base_assignment_validation",
  "current_gate": "G4_conditional_go",
  "repro_manifest": "experiments/manifests/oscar_lic_12h_repro_manifest_2026_06_25.yaml",
  "corrected_mlicpp_checkpoint_sha256": "67af8c950a4e8ae03da9bc95b87d13fd7831063ad12b7df1f872154e0082c559",
  "promoted_actual_mean_bpp": 3.849649,
  "promoted_tesseract_unicode_edit_delta": -8,
  "promoted_tesseract_latin_alnum_edit_delta": -8,
  "promoted_parseq_delta": "unchanged",
  "external_datasets_bundled": false,
  "external_checkpoints_bundled": false,
  "external_repositories_bundled": false,
  "manifest_excludes": [
    "MANIFEST.sha256"
  ]
}
